localflare/__init__.py
localflare-0.1.0.dist-info/licenses/LICENSE
localflare-0.1.0.dist-info/METADATA
localflare-0.1.0.dist-info/WHEEL
localflare-0.1.0.dist-info/top_level.txt
localflare-0.1.0.dist-info/RECORD
